{"AYekD9iJV4t5hXODT3/uRg==":"logo%E6%85%A7%E6%97%A5%E8%AC%9B%E5%A0%82-122x74.png","pa5Dkwo/T1qgW/t0h+fQvA==":"background5.jpg","k+iBxwBhqoI8sQnCTeZ0Kg==":"mbr-1046x709.jpeg","U4gRrJXWOgnIArZ5RGRYLg==":"mbr-3-1046x697.jpeg","mIIbxW0r7dEZSbMPwcoYdg==":"background2.jpg","sT80Y4RCGNBrSInGgrjIuA==":"background3.jpg","UAc7kepzJPkrSn4uqTRvmw==":"background4.jpg","OM6hTwqMAQpTVhLcPG86xg==":"background1.jpg","L67t1A/XqELNZaWRt+Dopg==":"mbr-1920x1441.jpg","ix6CdK9xYJlAxJHwiyaUzA==":"mbr-1-1046x709.jpeg","oA0FQfwfS5dMJcyFiohzSw==":"mbr-2-1046x709.jpeg","piEyABBcUO/atzEmXStvvA==":"mbr-1920x1441.jpeg"}